{"frames": {

"Morty_Arm0000":
{
	"frame": {"x":499,"y":2,"w":9,"h":31},
	"rotated": false,
	"trimmed": false,
	"spriteSourceSize": {"x":0,"y":0,"w":9,"h":31},
	"sourceSize": {"w":9,"h":31}
},
"Morty_Arm_Flesh0000":
{
	"frame": {"x":499,"y":35,"w":9,"h":30},
	"rotated": false,
	"trimmed": false,
	"spriteSourceSize": {"x":0,"y":0,"w":9,"h":30},
	"sourceSize": {"w":9,"h":30}
},
"Morty_Belly0000":
{
	"frame": {"x":164,"y":501,"w":58,"h":38},
	"rotated": false,
	"trimmed": false,
	"spriteSourceSize": {"x":0,"y":0,"w":58,"h":38},
	"sourceSize": {"w":58,"h":38}
},
"Morty_Belly_Flesh0000":
{
	"frame": {"x":45,"y":522,"w":58,"h":38},
	"rotated": false,
	"trimmed": false,
	"spriteSourceSize": {"x":0,"y":0,"w":58,"h":38},
	"sourceSize": {"w":58,"h":38}
},
"Morty_Core0000":
{
	"frame": {"x":426,"y":176,"w":64,"h":80},
	"rotated": false,
	"trimmed": false,
	"spriteSourceSize": {"x":0,"y":0,"w":64,"h":80},
	"sourceSize": {"w":64,"h":80}
},
"Morty_Core_Flesh0000":
{
	"frame": {"x":90,"y":180,"w":64,"h":80},
	"rotated": false,
	"trimmed": false,
	"spriteSourceSize": {"x":0,"y":0,"w":64,"h":80},
	"sourceSize": {"w":64,"h":80}
},
"Morty_Eye0000":
{
	"frame": {"x":482,"y":258,"w":19,"h":20},
	"rotated": false,
	"trimmed": false,
	"spriteSourceSize": {"x":0,"y":0,"w":19,"h":20},
	"sourceSize": {"w":19,"h":20}
},
"Morty_Eye_Closed0000":
{
	"frame": {"x":482,"y":280,"w":19,"h":20},
	"rotated": false,
	"trimmed": false,
	"spriteSourceSize": {"x":0,"y":0,"w":19,"h":20},
	"sourceSize": {"w":19,"h":20}
},
"Morty_Feet0000":
{
	"frame": {"x":90,"y":262,"w":66,"h":21},
	"rotated": false,
	"trimmed": false,
	"spriteSourceSize": {"x":0,"y":0,"w":66,"h":21},
	"sourceSize": {"w":66,"h":21}
},
"Morty_Feet_Flesh0000":
{
	"frame": {"x":473,"y":396,"w":31,"h":11},
	"rotated": false,
	"trimmed": false,
	"spriteSourceSize": {"x":0,"y":0,"w":31,"h":11},
	"sourceSize": {"w":31,"h":11}
},
"Morty_Hand0000":
{
	"frame": {"x":154,"y":400,"w":19,"h":17},
	"rotated": false,
	"trimmed": false,
	"spriteSourceSize": {"x":0,"y":0,"w":19,"h":17},
	"sourceSize": {"w":19,"h":17}
},
"Morty_Hand_Flesh0000":
{
	"frame": {"x":483,"y":409,"w":19,"h":17},
	"rotated": false,
	"trimmed": false,
	"spriteSourceSize": {"x":0,"y":0,"w":19,"h":17},
	"sourceSize": {"w":19,"h":17}
},
"Morty_Head_Flesh0000":
{
	"frame": {"x":2,"y":293,"w":69,"h":62},
	"rotated": false,
	"trimmed": false,
	"spriteSourceSize": {"x":0,"y":0,"w":69,"h":62},
	"sourceSize": {"w":69,"h":62}
},
"Morty_Head_Idle0000":
{
	"frame": {"x":402,"y":347,"w":69,"h":62},
	"rotated": false,
	"trimmed": false,
	"spriteSourceSize": {"x":0,"y":0,"w":69,"h":62},
	"sourceSize": {"w":69,"h":62}
},
"Morty_Leg0000":
{
	"frame": {"x":482,"y":116,"w":12,"h":42},
	"rotated": false,
	"trimmed": false,
	"spriteSourceSize": {"x":0,"y":0,"w":12,"h":42},
	"sourceSize": {"w":12,"h":42}
},
"Morty_Leg_Flesh0000":
{
	"frame": {"x":496,"y":116,"w":12,"h":42},
	"rotated": false,
	"trimmed": false,
	"spriteSourceSize": {"x":0,"y":0,"w":12,"h":42},
	"sourceSize": {"w":12,"h":42}
},
"Morty_Shoulder0000":
{
	"frame": {"x":482,"y":2,"w":15,"h":36},
	"rotated": false,
	"trimmed": false,
	"spriteSourceSize": {"x":0,"y":0,"w":15,"h":36},
	"sourceSize": {"w":15,"h":36}
},
"Morty_ShoulderLeft0000":
{
	"frame": {"x":482,"y":78,"w":15,"h":36},
	"rotated": false,
	"trimmed": false,
	"spriteSourceSize": {"x":0,"y":0,"w":15,"h":36},
	"sourceSize": {"w":15,"h":36}
},
"Morty_ShoulderLeft_Flesh0000":
{
	"frame": {"x":482,"y":40,"w":15,"h":36},
	"rotated": false,
	"trimmed": false,
	"spriteSourceSize": {"x":0,"y":0,"w":15,"h":36},
	"sourceSize": {"w":15,"h":36}
},
"Morty_Shoulder_Flesh0000":
{
	"frame": {"x":482,"y":40,"w":15,"h":36},
	"rotated": false,
	"trimmed": false,
	"spriteSourceSize": {"x":0,"y":0,"w":15,"h":36},
	"sourceSize": {"w":15,"h":36}
},
"Morty_Thigh0000":
{
	"frame": {"x":473,"y":347,"w":30,"h":47},
	"rotated": false,
	"trimmed": false,
	"spriteSourceSize": {"x":0,"y":0,"w":30,"h":47},
	"sourceSize": {"w":30,"h":47}
},
"Morty_Thigh_Flesh0000":
{
	"frame": {"x":121,"y":450,"w":30,"h":47},
	"rotated": false,
	"trimmed": false,
	"spriteSourceSize": {"x":0,"y":0,"w":30,"h":47},
	"sourceSize": {"w":30,"h":47}
},
"Rick_Arm0000":
{
	"frame": {"x":471,"y":485,"w":36,"h":57},
	"rotated": false,
	"trimmed": false,
	"spriteSourceSize": {"x":0,"y":0,"w":36,"h":57},
	"sourceSize": {"w":36,"h":57}
},
"Rick_Arm0001":
{
	"frame": {"x":299,"y":523,"w":36,"h":57},
	"rotated": false,
	"trimmed": false,
	"spriteSourceSize": {"x":0,"y":0,"w":36,"h":57},
	"sourceSize": {"w":36,"h":57}
},
"Rick_Arm0002":
{
	"frame": {"x":2,"y":530,"w":36,"h":57},
	"rotated": false,
	"trimmed": false,
	"spriteSourceSize": {"x":0,"y":0,"w":36,"h":57},
	"sourceSize": {"w":36,"h":57}
},
"Rick_Arm0003":
{
	"frame": {"x":164,"y":541,"w":36,"h":57},
	"rotated": false,
	"trimmed": false,
	"spriteSourceSize": {"x":0,"y":0,"w":36,"h":57},
	"sourceSize": {"w":36,"h":57}
},
"Rick_Arm_Flesh0000":
{
	"frame": {"x":202,"y":541,"w":36,"h":57},
	"rotated": false,
	"trimmed": false,
	"spriteSourceSize": {"x":0,"y":0,"w":36,"h":57},
	"sourceSize": {"w":36,"h":57}
},
"Rick_Belly0000":
{
	"frame": {"x":178,"y":377,"w":74,"h":48},
	"rotated": false,
	"trimmed": true,
	"spriteSourceSize": {"x":0,"y":1,"w":74,"h":49},
	"sourceSize": {"w":74,"h":49}
},
"Rick_Belly0001":
{
	"frame": {"x":254,"y":377,"w":74,"h":48},
	"rotated": false,
	"trimmed": true,
	"spriteSourceSize": {"x":0,"y":1,"w":74,"h":49},
	"sourceSize": {"w":74,"h":49}
},
"Rick_Belly0002":
{
	"frame": {"x":2,"y":357,"w":74,"h":49},
	"rotated": false,
	"trimmed": false,
	"spriteSourceSize": {"x":0,"y":0,"w":74,"h":49},
	"sourceSize": {"w":74,"h":49}
},
"Rick_Belly0003":
{
	"frame": {"x":78,"y":400,"w":74,"h":48},
	"rotated": false,
	"trimmed": true,
	"spriteSourceSize": {"x":0,"y":1,"w":74,"h":49},
	"sourceSize": {"w":74,"h":49}
},
"Rick_Belly_Flesh0000":
{
	"frame": {"x":2,"y":408,"w":74,"h":48},
	"rotated": false,
	"trimmed": false,
	"spriteSourceSize": {"x":0,"y":0,"w":74,"h":48},
	"sourceSize": {"w":74,"h":48}
},
"Rick_Core0000":
{
	"frame": {"x":162,"y":2,"w":78,"h":172},
	"rotated": false,
	"trimmed": true,
	"spriteSourceSize": {"x":0,"y":5,"w":78,"h":177},
	"sourceSize": {"w":78,"h":177}
},
"Rick_Core0001":
{
	"frame": {"x":242,"y":2,"w":78,"h":172},
	"rotated": false,
	"trimmed": true,
	"spriteSourceSize": {"x":0,"y":5,"w":78,"h":177},
	"sourceSize": {"w":78,"h":177}
},
"Rick_Core0002":
{
	"frame": {"x":2,"y":2,"w":78,"h":177},
	"rotated": false,
	"trimmed": false,
	"spriteSourceSize": {"x":0,"y":0,"w":78,"h":177},
	"sourceSize": {"w":78,"h":177}
},
"Rick_Core0003":
{
	"frame": {"x":82,"y":2,"w":78,"h":176},
	"rotated": false,
	"trimmed": true,
	"spriteSourceSize": {"x":0,"y":1,"w":78,"h":177},
	"sourceSize": {"w":78,"h":177}
},
"Rick_Core_Flesh0000":
{
	"frame": {"x":322,"y":2,"w":78,"h":172},
	"rotated": false,
	"trimmed": false,
	"spriteSourceSize": {"x":0,"y":0,"w":78,"h":172},
	"sourceSize": {"w":78,"h":172}
},
"Rick_Core_Flesh0001":
{
	"frame": {"x":402,"y":2,"w":78,"h":172},
	"rotated": false,
	"trimmed": true,
	"spriteSourceSize": {"x":0,"y":0,"w":78,"h":172},
	"sourceSize": {"w":78,"h":172}
},
"Rick_Eye0000":
{
	"frame": {"x":402,"y":288,"w":19,"h":20},
	"rotated": false,
	"trimmed": true,
	"spriteSourceSize": {"x":2,"y":0,"w":21,"h":20},
	"sourceSize": {"w":21,"h":20}
},
"Rick_Eye0001":
{
	"frame": {"x":402,"y":288,"w":19,"h":20},
	"rotated": false,
	"trimmed": true,
	"spriteSourceSize": {"x":2,"y":0,"w":21,"h":20},
	"sourceSize": {"w":21,"h":20}
},
"Rick_Eye0002":
{
	"frame": {"x":482,"y":160,"w":18,"h":14},
	"rotated": false,
	"trimmed": true,
	"spriteSourceSize": {"x":0,"y":3,"w":21,"h":20},
	"sourceSize": {"w":21,"h":20}
},
"Rick_Eye0003":
{
	"frame": {"x":482,"y":324,"w":19,"h":18},
	"rotated": false,
	"trimmed": true,
	"spriteSourceSize": {"x":2,"y":2,"w":21,"h":20},
	"sourceSize": {"w":21,"h":20}
},
"Rick_EyeBrow0000":
{
	"frame": {"x":299,"y":427,"w":29,"h":9},
	"rotated": false,
	"trimmed": false,
	"spriteSourceSize": {"x":0,"y":0,"w":29,"h":9},
	"sourceSize": {"w":29,"h":9}
},
"Rick_Eye_Closed0000":
{
	"frame": {"x":482,"y":302,"w":19,"h":20},
	"rotated": false,
	"trimmed": true,
	"spriteSourceSize": {"x":2,"y":0,"w":21,"h":20},
	"sourceSize": {"w":21,"h":20}
},
"Rick_Eye_Closed0001":
{
	"frame": {"x":402,"y":310,"w":19,"h":20},
	"rotated": false,
	"trimmed": true,
	"spriteSourceSize": {"x":2,"y":0,"w":21,"h":20},
	"sourceSize": {"w":21,"h":20}
},
"Rick_Eye_Closed0002":
{
	"frame": {"x":492,"y":176,"w":18,"h":14},
	"rotated": false,
	"trimmed": true,
	"spriteSourceSize": {"x":0,"y":3,"w":21,"h":20},
	"sourceSize": {"w":21,"h":20}
},
"Rick_Eye_Closed0003":
{
	"frame": {"x":381,"y":377,"w":19,"h":18},
	"rotated": false,
	"trimmed": true,
	"spriteSourceSize": {"x":2,"y":2,"w":21,"h":20},
	"sourceSize": {"w":21,"h":20}
},
"Rick_Feet0000":
{
	"frame": {"x":88,"y":573,"w":66,"h":21},
	"rotated": false,
	"trimmed": false,
	"spriteSourceSize": {"x":0,"y":0,"w":66,"h":21},
	"sourceSize": {"w":66,"h":21}
},
"Rick_Feet0001":
{
	"frame": {"x":88,"y":596,"w":66,"h":21},
	"rotated": false,
	"trimmed": false,
	"spriteSourceSize": {"x":0,"y":0,"w":66,"h":21},
	"sourceSize": {"w":66,"h":21}
},
"Rick_Feet0002":
{
	"frame": {"x":288,"y":599,"w":66,"h":21},
	"rotated": false,
	"trimmed": false,
	"spriteSourceSize": {"x":0,"y":0,"w":66,"h":21},
	"sourceSize": {"w":66,"h":21}
},
"Rick_Feet0003":
{
	"frame": {"x":356,"y":599,"w":66,"h":21},
	"rotated": false,
	"trimmed": false,
	"spriteSourceSize": {"x":0,"y":0,"w":66,"h":21},
	"sourceSize": {"w":66,"h":21}
},
"Rick_Feet_Flesh0000":
{
	"frame": {"x":424,"y":599,"w":66,"h":21},
	"rotated": false,
	"trimmed": false,
	"spriteSourceSize": {"x":0,"y":0,"w":66,"h":21},
	"sourceSize": {"w":66,"h":21}
},
"Rick_Hand0000":
{
	"frame": {"x":337,"y":557,"w":46,"h":40},
	"rotated": false,
	"trimmed": false,
	"spriteSourceSize": {"x":0,"y":0,"w":46,"h":40},
	"sourceSize": {"w":46,"h":40}
},
"Rick_Hand0001":
{
	"frame": {"x":385,"y":557,"w":46,"h":40},
	"rotated": false,
	"trimmed": false,
	"spriteSourceSize": {"x":0,"y":0,"w":46,"h":40},
	"sourceSize": {"w":46,"h":40}
},
"Rick_Hand0002":
{
	"frame": {"x":433,"y":557,"w":46,"h":40},
	"rotated": false,
	"trimmed": false,
	"spriteSourceSize": {"x":0,"y":0,"w":46,"h":40},
	"sourceSize": {"w":46,"h":40}
},
"Rick_Hand0003":
{
	"frame": {"x":40,"y":562,"w":46,"h":40},
	"rotated": false,
	"trimmed": false,
	"spriteSourceSize": {"x":0,"y":0,"w":46,"h":40},
	"sourceSize": {"w":46,"h":40}
},
"Rick_Hand_Flesh0000":
{
	"frame": {"x":240,"y":571,"w":46,"h":40},
	"rotated": false,
	"trimmed": false,
	"spriteSourceSize": {"x":0,"y":0,"w":46,"h":40},
	"sourceSize": {"w":46,"h":40}
},
"Rick_Head_Flesh0000":
{
	"frame": {"x":162,"y":176,"w":86,"h":110},
	"rotated": false,
	"trimmed": false,
	"spriteSourceSize": {"x":0,"y":0,"w":86,"h":110},
	"sourceSize": {"w":86,"h":110}
},
"Rick_Head_Idle0000":
{
	"frame": {"x":250,"y":176,"w":86,"h":110},
	"rotated": false,
	"trimmed": false,
	"spriteSourceSize": {"x":0,"y":0,"w":86,"h":110},
	"sourceSize": {"w":86,"h":110}
},
"Rick_Head_Idle0001":
{
	"frame": {"x":338,"y":176,"w":86,"h":110},
	"rotated": false,
	"trimmed": false,
	"spriteSourceSize": {"x":0,"y":0,"w":86,"h":110},
	"sourceSize": {"w":86,"h":110}
},
"Rick_Head_Idle0002":
{
	"frame": {"x":2,"y":181,"w":86,"h":110},
	"rotated": false,
	"trimmed": false,
	"spriteSourceSize": {"x":0,"y":0,"w":86,"h":110},
	"sourceSize": {"w":86,"h":110}
},
"Rick_Head_Idle0003":
{
	"frame": {"x":90,"y":288,"w":86,"h":110},
	"rotated": false,
	"trimmed": false,
	"spriteSourceSize": {"x":0,"y":0,"w":86,"h":110},
	"sourceSize": {"w":86,"h":110}
},
"Rick_Leg0000":
{
	"frame": {"x":330,"y":377,"w":49,"h":72},
	"rotated": false,
	"trimmed": false,
	"spriteSourceSize": {"x":0,"y":0,"w":49,"h":72},
	"sourceSize": {"w":49,"h":72}
},
"Rick_Leg0001":
{
	"frame": {"x":381,"y":411,"w":49,"h":72},
	"rotated": false,
	"trimmed": false,
	"spriteSourceSize": {"x":0,"y":0,"w":49,"h":72},
	"sourceSize": {"w":49,"h":72}
},
"Rick_Leg0002":
{
	"frame": {"x":432,"y":411,"w":49,"h":72},
	"rotated": false,
	"trimmed": false,
	"spriteSourceSize": {"x":0,"y":0,"w":49,"h":72},
	"sourceSize": {"w":49,"h":72}
},
"Rick_Leg0003":
{
	"frame": {"x":154,"y":427,"w":49,"h":72},
	"rotated": false,
	"trimmed": false,
	"spriteSourceSize": {"x":0,"y":0,"w":49,"h":72},
	"sourceSize": {"w":49,"h":72}
},
"Rick_Leg_Flesh0000":
{
	"frame": {"x":205,"y":427,"w":49,"h":72},
	"rotated": false,
	"trimmed": false,
	"spriteSourceSize": {"x":0,"y":0,"w":49,"h":72},
	"sourceSize": {"w":49,"h":72}
},
"Rick_Shoulder0000":
{
	"frame": {"x":256,"y":427,"w":41,"h":70},
	"rotated": false,
	"trimmed": false,
	"spriteSourceSize": {"x":0,"y":0,"w":41,"h":70},
	"sourceSize": {"w":41,"h":70}
},
"Rick_Shoulder0001":
{
	"frame": {"x":78,"y":450,"w":41,"h":70},
	"rotated": false,
	"trimmed": false,
	"spriteSourceSize": {"x":0,"y":0,"w":41,"h":70},
	"sourceSize": {"w":41,"h":70}
},
"Rick_Shoulder0002":
{
	"frame": {"x":299,"y":451,"w":41,"h":70},
	"rotated": false,
	"trimmed": false,
	"spriteSourceSize": {"x":0,"y":0,"w":41,"h":70},
	"sourceSize": {"w":41,"h":70}
},
"Rick_Shoulder0003":
{
	"frame": {"x":2,"y":458,"w":41,"h":70},
	"rotated": false,
	"trimmed": false,
	"spriteSourceSize": {"x":0,"y":0,"w":41,"h":70},
	"sourceSize": {"w":41,"h":70}
},
"Rick_ShoulderLeft0000":
{
	"frame": {"x":385,"y":485,"w":41,"h":70},
	"rotated": false,
	"trimmed": false,
	"spriteSourceSize": {"x":0,"y":0,"w":41,"h":70},
	"sourceSize": {"w":41,"h":70}
},
"Rick_ShoulderLeft0001":
{
	"frame": {"x":428,"y":485,"w":41,"h":70},
	"rotated": false,
	"trimmed": false,
	"spriteSourceSize": {"x":0,"y":0,"w":41,"h":70},
	"sourceSize": {"w":41,"h":70}
},
"Rick_ShoulderLeft0002":
{
	"frame": {"x":256,"y":499,"w":41,"h":70},
	"rotated": false,
	"trimmed": false,
	"spriteSourceSize": {"x":0,"y":0,"w":41,"h":70},
	"sourceSize": {"w":41,"h":70}
},
"Rick_ShoulderLeft0003":
{
	"frame": {"x":121,"y":501,"w":41,"h":70},
	"rotated": false,
	"trimmed": false,
	"spriteSourceSize": {"x":0,"y":0,"w":41,"h":70},
	"sourceSize": {"w":41,"h":70}
},
"Rick_ShoulderLeft_Flesh0000":
{
	"frame": {"x":342,"y":485,"w":41,"h":70},
	"rotated": false,
	"trimmed": false,
	"spriteSourceSize": {"x":0,"y":0,"w":41,"h":70},
	"sourceSize": {"w":41,"h":70}
},
"Rick_Shoulder_Flesh0000":
{
	"frame": {"x":342,"y":485,"w":41,"h":70},
	"rotated": false,
	"trimmed": false,
	"spriteSourceSize": {"x":0,"y":0,"w":41,"h":70},
	"sourceSize": {"w":41,"h":70}
},
"Rick_Thigh0000":
{
	"frame": {"x":426,"y":258,"w":54,"h":87},
	"rotated": false,
	"trimmed": false,
	"spriteSourceSize": {"x":0,"y":0,"w":54,"h":87},
	"sourceSize": {"w":54,"h":87}
},
"Rick_Thigh0001":
{
	"frame": {"x":178,"y":288,"w":54,"h":87},
	"rotated": false,
	"trimmed": false,
	"spriteSourceSize": {"x":0,"y":0,"w":54,"h":87},
	"sourceSize": {"w":54,"h":87}
},
"Rick_Thigh0002":
{
	"frame": {"x":234,"y":288,"w":54,"h":87},
	"rotated": false,
	"trimmed": false,
	"spriteSourceSize": {"x":0,"y":0,"w":54,"h":87},
	"sourceSize": {"w":54,"h":87}
},
"Rick_Thigh0003":
{
	"frame": {"x":290,"y":288,"w":54,"h":87},
	"rotated": false,
	"trimmed": false,
	"spriteSourceSize": {"x":0,"y":0,"w":54,"h":87},
	"sourceSize": {"w":54,"h":87}
},
"Rick_Thigh_Flesh0000":
{
	"frame": {"x":346,"y":288,"w":54,"h":87},
	"rotated": false,
	"trimmed": false,
	"spriteSourceSize": {"x":0,"y":0,"w":54,"h":87},
	"sourceSize": {"w":54,"h":87}
}},
"meta": {
	"app": "Adobe Animate",
	"version": "19.1.0.349",
	"image": "RickAndMorty.png",
	"format": "RGBA8888",
	"size": {"w":512,"h":1024},
	"scale": "1"
}
}
